[
  {
    "left_category": "ncaab_champ",
    "right_category": "ncaab_10rpg",
    "left_label": "NCAA Champion (M)",
    "right_label": "10+ RPG in College (M)",
    "valid_players": [
      "Anthony Davis",
      "Bill Russell",
      "Bill Walton",
      "Carmelo Anthony",
      "Lew Alcindor"
    ],
    "answer_count": 5
  },
  {
    "left_category": "ncaab_10rpg",
    "right_category": "born_70s",
    "left_label": "10+ RPG in College (M)",
    "right_label": "Born in the 1970s",
    "valid_players": [
      "Shaquille O'Neal",
      "Tim Duncan"
    ],
    "answer_count": 2
  },
  {
    "left_category": "born_70s",
    "right_category": "ncaab_forward",
    "left_label": "Born in the 1970s",
    "right_label": "College Forward (M)",
    "valid_players": [
      "Glenn Robinson",
      "Grant Hill"
    ],
    "answer_count": 2
  },
  {
    "left_category": "ncaab_forward",
    "right_category": "college_usc",
    "left_label": "College Forward (M)",
    "right_label": "Went to USC",
    "valid_players": [
      "Evan Mobley",
      "Nikola Vucevic",
      "Taj Gibson"
    ],
    "answer_count": 3
  },
  {
    "left_category": "college_usc",
    "right_category": "ncaab_forward",
    "left_label": "Went to USC",
    "right_label": "College Forward (M)",
    "valid_players": [
      "Evan Mobley",
      "Nikola Vucevic",
      "Taj Gibson"
    ],
    "answer_count": 3
  },
  {
    "left_category": "ncaab_forward",
    "right_category": "ncaab_ucla",
    "left_label": "College Forward (M)",
    "right_label": "Played at UCLA (M)",
    "valid_players": [
      "Kevon Looney",
      "Moses Brown",
      "T.J. Leaf"
    ],
    "answer_count": 3
  },
  {
    "left_category": "ncaab_ucla",
    "right_category": "ncaab_guard",
    "left_label": "Played at UCLA (M)",
    "right_label": "College Guard (M)",
    "valid_players": [
      "Jordan Adams",
      "Kyle Anderson",
      "Lonzo Ball",
      "Shabazz Muhammad"
    ],
    "answer_count": 4
  },
  {
    "left_category": "ncaab_guard",
    "right_category": "ncaab_25ppg",
    "left_label": "College Guard (M)",
    "right_label": "25+ PPG in College (M)",
    "valid_players": [
      "Andre Collins",
      "Antoine Davis",
      "Gary Neal",
      "Kevin Durant",
      "Keydren (Keekee) Clark",
      "Lester Hudson",
      "Oscar Robertson",
      "Pete Maravich",
      "Trae Young",
      "Trey Johnson"
    ],
    "answer_count": 10
  },
  {
    "left_category": "ncaab_25ppg",
    "right_category": "ncaab_10rpg",
    "left_label": "25+ PPG in College (M)",
    "right_label": "10+ RPG in College (M)",
    "valid_players": [
      "Elgin Baylor",
      "Kevin Durant",
      "Lamine Diane",
      "Larry Bird",
      "Lew Alcindor",
      "Michael Beasley",
      "Oscar Robertson",
      "Wilt Chamberlain"
    ],
    "answer_count": 8
  },
  {
    "left_category": "ncaab_10rpg",
    "right_category": "college_texas",
    "left_label": "10+ RPG in College (M)",
    "right_label": "Went to Texas",
    "valid_players": [
      "Kevin Durant",
      "Mo Bamba"
    ],
    "answer_count": 2
  },
  {
    "left_category": "college_texas",
    "right_category": "ncaab_forward",
    "left_label": "Went to Texas",
    "right_label": "College Forward (M)",
    "valid_players": [
      "Jarrett Allen",
      "LaMarcus Aldridge",
      "Mo Bamba",
      "P.J. Tucker"
    ],
    "answer_count": 4
  },
  {
    "left_category": "ncaab_forward",
    "right_category": "decade_10s",
    "left_label": "College Forward (M)",
    "right_label": "Played in 2010s",
    "valid_players": [
      "AJ West",
      "Aaron Anderson",
      "Abdul Lewis",
      "Adnan Hodzic",
      "Adom Jacko",
      "Al-Farouq Aminu",
      "Alec Peters",
      "Alex Francis",
      "Alexis Yetna",
      "Alize Johnson",
      "Andre Roberson",
      "Andrew Gonzalez",
      "Andrew Nicholson",
      "Anthony Bennett",
      "Anthony Davis",
      "Anthony Lamb",
      "Arnett Moultrie",
      "Arsalan Kazemi",
      "Augustine Rubit",
      "Averyl Ugba",
      "Ben Simmons",
      "Brandon Bowdry",
      "Brandon Ingram",
      "Brandon McCoy",
      "Brian Voelkel",
      "Bruno Fernando",
      "Bryce Washington",
      "CJ Elleby",
      "Caleb Swanigan",
      "Cameron Oliver",
      "Carlos Dotson",
      "Charles Garcia",
      "Charlie Brown Jr.",
      "Chavaughn Lewis",
      "Chehales Tapscott",
      "Chima Moneke",
      "Chris Gaston",
      "Cinmeon Bowers",
      "Cletrell Pope",
      "Cleveland Melvin",
      "Cody Zeller",
      "Corey Petros",
      "Craig Brackins",
      "Damian Saunders",
      "David Laury",
      "De'jon Davis",
      "DeMarcus Cousins",
      "Deandre Ayton",
      "Dedric Lawson",
      "Demajeo Wiggins",
      "Dennis Tinnon",
      "Derek Culver",
      "Derick Newton",
      "Derrick Barden",
      "Derrick Favors",
      "Derrick Griffin",
      "Derrick Williams",
      "Desharick Guidry",
      "Desmond Williams",
      "Devin Thomas",
      "Devin Williams",
      "Devontae Cacok",
      "Dikembe Dixson",
      "Dior Lowhorn",
      "Domantas Sabonis",
      "Dominique Morrison",
      "Doug McDermott",
      "Drew McDonald",
      "Eli Holman",
      "Elijah Pittman",
      "Emanuel Littles",
      "Emmanuel Omogbo",
      "Eric Moreland",
      "Ethan Happ",
      "Fardaws Aimaq",
      "Gary Clark",
      "Gary Flowers",
      "Geddes Robinson",
      "George Odufuwa",
      "Gilberto Clavell",
      "Harrison Barnes",
      "Hasahn French",
      "Hassan Whiteside",
      "Henry Ellenson",
      "Herb Pope",
      "Iba Camara",
      "Ike Azotam",
      "Ivan Rabb",
      "Jabari Parker",
      "Jakob Poeltl",
      "Jalen Cannon",
      "Jalen Smith",
      "Jameel McKay",
      "Jameel Warney",
      "Jamelle Hagins",
      "James Butler",
      "James Daniel III",
      "James Dickey",
      "James Webb III",
      "Jared Sullinger",
      "Jarnell Stokes",
      "Jarrett Allen",
      "Jarrod Jones",
      "Jarvis Williams",
      "Javonte Green",
      "Jayden Gardner",
      "Jayson Tatum",
      "Jayveous McKinnis",
      "Jeff Allen",
      "Jeffrey Solarin",
      "Jemerrio Jones",
      "Jeremy Combs",
      "Jeromy Rodriguez",
      "Jimmy Hall",
      "Joel Bolomboy",
      "John Brown",
      "John Henson",
      "John Mooney",
      "Jonathan Rodriguez",
      "Jordan Caroline",
      "Jordan Glynn",
      "Jordan Mickey",
      "Jordan Murphy",
      "Jordan Washington",
      "Jordan Williams",
      "Jordon Varnado",
      "Joseph Harris",
      "Joseph Lopez",
      "Josh Hawkinson",
      "Julian Boyd",
      "Julius Randle",
      "Justin Bean",
      "Justin Nabors",
      "Justin Rutty",
      "Kawhi Leonard",
      "Keith Rendleman",
      "Kelvin Martin",
      "Ken Horton",
      "Kenneth Faried",
      "Kevin Hervey",
      "Kevin Marfo",
      "Kevin Thompson",
      "Kevon Looney",
      "Kyle Singler",
      "LaDaris Green",
      "Lamar Stevens",
      "Lamine Diane",
      "Lavoy Allen",
      "Lenny Daniel",
      "Leonard Harper-Baker",
      "Luke Babbitt",
      "Luke Harangody",
      "Mac Koshwal",
      "Majok Majok",
      "Malcolm Thomas",
      "Mamadou Seck",
      "Markeith Cummings",
      "Marquis Gilstrap",
      "Marqus Blakely",
      "Marvin Bagley III",
      "Mason Plumlee",
      "Mike Daum",
      "Mike Glover",
      "Mike Watkins",
      "Mo Bamba",
      "Moses Brown",
      "Murphy Holloway",
      "Nathan Knight",
      "Nick Mayo",
      "Nikola Vucevic",
      "Noah Horchler",
      "Noah Vonleh",
      "O.D. Anosike",
      "Obi Toppin",
      "Obinna Oleka",
      "Oshae Brissett",
      "Ousmane Drame",
      "Pascal Siakam",
      "Patrick Patterson",
      "Peyton Aldridge",
      "Phillip Carr",
      "Quintin Dove",
      "RJ Barrett",
      "Rashad Savage",
      "Rashawn Thomas",
      "Reggie Perry",
      "Richard Howell",
      "Rico Gathers",
      "Robert Glenn",
      "Robert Williams III",
      "Rokas Gustys",
      "Royce White",
      "Ryan Anderson",
      "Ryan Martin",
      "Ryan Rossiter",
      "Ryan Wittman",
      "Samuel Givens",
      "Shakur Juiston",
      "Shawn Long",
      "Stan Okoye",
      "Steffon Mitchell",
      "Stephen Maxwell",
      "Stephen Zimmerman",
      "T.J. Leaf",
      "T.J. Robinson",
      "T.J. Warren",
      "TaShawn Thomas",
      "Tanner Leissner",
      "Terell Parks",
      "Terrell Miller Jr.",
      "Terrence Jones",
      "Tim Williams",
      "Tiny Gallon",
      "Tommy Brenton",
      "Tony Mitchell",
      "Torrey Craig",
      "Tres Tinkle",
      "Trevor Mbakwe",
      "Tyler Cain",
      "Tyler Kohl",
      "Venky Jois",
      "Wendell Carter Jr.",
      "Wendell McKines",
      "Wil Carter",
      "Willie Jackson",
      "Yoeli Childs",
      "Zac Cuthbertson",
      "Zion Williamson",
      "Zvonko Buljan"
    ],
    "answer_count": 229
  },
  {
    "left_category": "decade_10s",
    "right_category": "decade_00s",
    "left_label": "Played in 2010s",
    "right_label": "Played in 2000s",
    "valid_players": [
      "Adnan Hodzic",
      "Adrian Oliver",
      "Al-Farouq Aminu",
      "Alex Young",
      "Anatoly Bose",
      "Andrew Goudelock",
      "Andrew Nicholson",
      "Anthony Johnson",
      "Antwan Carter",
      "Arnett Moultrie",
      "Artsiom Parakhouski",
      "Aubrey Coleman",
      "Austin Kenon",
      "Ben Smith",
      "Brandon Bowdry",
      "Cameron Wells",
      "Charles Jenkins",
      "Chris Warren",
      "Corey Allmond",
      "Corey Lowe",
      "Courtney Fortson",
      "Craig Brackins",
      "Damian Lillard",
      "Damian Saunders",
      "Damion James",
      "David Kool",
      "Devan Downey",
      "Dior Lowhorn",
      "Dominique Jones",
      "Dominique Morrison",
      "Donald Sims",
      "Eli Holman",
      "Geddes Robinson",
      "George Odufuwa",
      "Greg Monroe",
      "Greivis Vasquez",
      "Herb Pope",
      "Isaiah Thomas",
      "Jahmar Young",
      "James Anderson",
      "James Florence",
      "Jarrod Jones",
      "Jeff Allen",
      "Jeremy Hazell",
      "Jimmer Fredette",
      "John Brown",
      "John Holland",
      "Johnathon Jones",
      "Jonathan Rodriguez",
      "Joseph Harris",
      "Julian Boyd",
      "Justin Nabors",
      "Justin Rutty",
      "Keith Benson",
      "Kelvin Martin",
      "Ken Horton",
      "Kenneth Faried",
      "Kevin Foster",
      "Kevin Palmer",
      "Kevin Thompson",
      "Klay Thompson",
      "Kyle O'Quinn",
      "Kyle Singler",
      "LaceDarius Dunn",
      "Lavoy Allen",
      "Luke Babbitt",
      "Luke Harangody",
      "Mac Koshwal",
      "Malcolm Delaney",
      "Malcolm Thomas",
      "Manny Harris",
      "Marqus Blakely",
      "Murphy Holloway",
      "Nick Barbour",
      "Nikola Vucevic",
      "Omar Samhan",
      "Orlando Johnson",
      "Patrick Patterson",
      "Randy Culpepper",
      "Reggie Hamilton",
      "Robert Glenn",
      "Ronald Moore",
      "Ryan Rossiter",
      "Ryan Wittman",
      "Samuel Givens",
      "Scott Machado",
      "Scottie Reynolds",
      "Shane Gibson",
      "Sylven Landesberg",
      "T.J. Robinson",
      "Talor Battle",
      "Tommy Brenton",
      "Trevor Mbakwe",
      "Tyler Cain",
      "Wendell McKines",
      "William Mosley",
      "Zvonko Buljan"
    ],
    "answer_count": 97
  },
  {
    "left_category": "decade_00s",
    "right_category": "college_michigan",
    "left_label": "Played in 2000s",
    "right_label": "Went to Michigan",
    "valid_players": [
      "Daniel Horton",
      "Manny Harris"
    ],
    "answer_count": 2
  },
  {
    "left_category": "college_michigan",
    "right_category": "decade_10s",
    "left_label": "Went to Michigan",
    "right_label": "Played in 2010s",
    "valid_players": [
      "Manny Harris",
      "Trey Burke"
    ],
    "answer_count": 2
  },
  {
    "left_category": "decade_10s",
    "right_category": "college_lsu",
    "left_label": "Played in 2010s",
    "right_label": "Went to LSU",
    "valid_players": [
      "Ben Simmons",
      "Jordan Mickey"
    ],
    "answer_count": 2
  },
  {
    "left_category": "college_lsu",
    "right_category": "ncaab_guard",
    "left_label": "Went to LSU",
    "right_label": "College Guard (M)",
    "valid_players": [
      "Cam Thomas",
      "Marcus Thornton",
      "Pete Maravich"
    ],
    "answer_count": 3
  },
  {
    "left_category": "ncaab_guard",
    "right_category": "ncaab_indiana",
    "left_label": "College Guard (M)",
    "right_label": "Played at Indiana (M)",
    "valid_players": [
      "Eric Gordon",
      "James Blackmon Jr.",
      "Romeo Langford"
    ],
    "answer_count": 3
  },
  {
    "left_category": "ncaab_indiana",
    "right_category": "decade_10s",
    "left_label": "Played at Indiana (M)",
    "right_label": "Played in 2010s",
    "valid_players": [
      "Cody Zeller",
      "James Blackmon Jr.",
      "Noah Vonleh",
      "Romeo Langford"
    ],
    "answer_count": 4
  },
  {
    "left_category": "decade_10s",
    "right_category": "ncaab_indiana",
    "left_label": "Played in 2010s",
    "right_label": "Played at Indiana (M)",
    "valid_players": [
      "Cody Zeller",
      "James Blackmon Jr.",
      "Noah Vonleh",
      "Romeo Langford"
    ],
    "answer_count": 4
  }
]