[
  {
    "left_category": "born_70s",
    "right_category": "ncaaw_poy",
    "left_label": "Born in the 1970s",
    "right_label": "College POY (W)",
    "valid_players": [
      "Chamique Holdsclaw",
      "Sheryl Swoopes",
      "Tamika Catchings"
    ],
    "answer_count": 3
  },
  {
    "left_category": "ncaaw_poy",
    "right_category": "decade_10s",
    "left_label": "College POY (W)",
    "right_label": "Played in 2010s",
    "valid_players": [
      "A'ja Wilson",
      "Breanna Stewart",
      "Brittney Griner",
      "Elena Delle Donne",
      "Maya Moore",
      "Nneka Ogwumike",
      "Sabrina Ionescu"
    ],
    "answer_count": 7
  },
  {
    "left_category": "decade_10s",
    "right_category": "college_ohio_st",
    "left_label": "Played in 2010s",
    "right_label": "Went to Ohio State",
    "valid_players": [
      "Aaliyah Patty",
      "Alexa Hart",
      "Ameryst Alston",
      "Amy Scullion",
      "Ashley Adams",
      "Asia Doss",
      "Braxtin Miller",
      "Cait Craft",
      "Darryce Moore",
      "Dorka Juhasz",
      "Janai Crooms",
      "Jensen Caretti",
      "Kelsey Mitchell",
      "Lisa Blair",
      "Makayla Waterman",
      "Martina Ellerbe",
      "Raven Ferguson",
      "Shayla Cooper",
      "Sierra Calhoun",
      "Tori McCoy"
    ],
    "answer_count": 20
  },
  {
    "left_category": "college_ohio_st",
    "right_category": "decade_20s",
    "left_label": "Went to Ohio State",
    "right_label": "Played in 2020s",
    "valid_players": [
      "Aaliyah Patty",
      "Ava Watson",
      "Braxtin Miller",
      "Bryn Martin",
      "Chance Gray",
      "Cotie McMahon",
      "Dorka Juhasz",
      "Eboni Walker",
      "Elsa Lemmila",
      "Hevynne Bristow",
      "Jacy Sheldon",
      "Jaloni Cambridge",
      "Janai Crooms",
      "Kateri Poole",
      "Kennedy Cambridge",
      "Kylee Kitts",
      "Madison Greene",
      "Rebeka Mikulasikova",
      "Rikki Harris",
      "Taylor Thierry"
    ],
    "answer_count": 20
  },
  {
    "left_category": "decade_20s",
    "right_category": "ncaaw_20ppg",
    "left_label": "Played in 2020s",
    "right_label": "20+ PPG in College (W)",
    "valid_players": [
      "Alissa Pili",
      "Aneesah Morrow",
      "Audi Crooks",
      "Caitlin Clark",
      "Chennedy Carter",
      "Dyaisha Fair",
      "Hannah Hidalgo",
      "JuJu Watkins",
      "Kiyomi McMiller",
      "Maddy Siegrist",
      "Mikayla Blakes",
      "Naomi White",
      "Raegan McCowan",
      "Rhyne Howard",
      "Ta'Niya Latson",
      "Taliah Scott"
    ],
    "answer_count": 16
  },
  {
    "left_category": "ncaaw_20ppg",
    "right_category": "ncaaw_iowa",
    "left_label": "20+ PPG in College (W)",
    "right_label": "Played at Iowa (W)",
    "valid_players": [
      "Caitlin Clark",
      "Megan Gustafson"
    ],
    "answer_count": 2
  },
  {
    "left_category": "ncaaw_iowa",
    "right_category": "decade_10s",
    "left_label": "Played at Iowa (W)",
    "right_label": "Played in 2010s",
    "valid_players": [
      "Alexa Kastanek",
      "Alexis Sevillian",
      "Ally Disterhoft",
      "Amanda Ollinger",
      "Bethany Doolittle",
      "Carly Mohns",
      "Chase Coley",
      "Christina Buttenham",
      "Claire Till",
      "Hannah Stewart",
      "Kali Peschel",
      "Kathleen Doyle",
      "Logan Cook",
      "Makenzie Meyer",
      "Megan Gustafson",
      "Melissa Dixon",
      "Monika Czinano",
      "Samantha Logic",
      "Tania Davis",
      "Theairra Taylor",
      "Tomi Taiwo"
    ],
    "answer_count": 21
  },
  {
    "left_category": "decade_10s",
    "right_category": "college_penn_st",
    "left_label": "Played in 2010s",
    "right_label": "Went to Penn State",
    "valid_players": [
      "Alisia Smith",
      "Amari Carter",
      "Ariel Edwards",
      "Ashanti Thomas",
      "Candice Agee",
      "Dara Taylor",
      "De'Janae Boykin",
      "Jaida Travascio-Green",
      "Jaylen Williams",
      "Kaliyah Mitchell",
      "Kamaria McDaniel",
      "Keke Sevillian",
      "Lauren Ebo",
      "Lindsey Spann",
      "Maggie Lucas",
      "Peyton Whitted",
      "Sierra Moore",
      "Siyeh Frazier",
      "Talia East",
      "Teniya Page",
      "Tori Waldner"
    ],
    "answer_count": 21
  },
  {
    "left_category": "college_penn_st",
    "right_category": "decade_20s",
    "left_label": "Went to Penn State",
    "right_label": "Played in 2020s",
    "valid_players": [
      "Ali Brigham",
      "Alisia Smith",
      "Alli Campbell",
      "Anna Camden",
      "Ashanti Thomas",
      "Chanaya Pinto",
      "Grace Hall",
      "Gracie Merkle",
      "Jayla Oden",
      "Kamaria McDaniel",
      "Kayla Thomas",
      "Kiyomi McMiller",
      "Lauren Ebo",
      "Leilani Kapinus",
      "Makenna Marisa",
      "Moriah Murray",
      "Nyla McFadden",
      "Sha'Lynn Hagans",
      "Siyeh Frazier",
      "Tea Cleante",
      "Viktoria Ranisavljevic",
      "Vitoria Santana"
    ],
    "answer_count": 22
  },
  {
    "left_category": "decade_20s",
    "right_category": "college_ohio_st",
    "left_label": "Played in 2020s",
    "right_label": "Went to Ohio State",
    "valid_players": [
      "Aaliyah Patty",
      "Ava Watson",
      "Braxtin Miller",
      "Bryn Martin",
      "Chance Gray",
      "Cotie McMahon",
      "Dorka Juhasz",
      "Eboni Walker",
      "Elsa Lemmila",
      "Hevynne Bristow",
      "Jacy Sheldon",
      "Jaloni Cambridge",
      "Janai Crooms",
      "Kateri Poole",
      "Kennedy Cambridge",
      "Kylee Kitts",
      "Madison Greene",
      "Rebeka Mikulasikova",
      "Rikki Harris",
      "Taylor Thierry"
    ],
    "answer_count": 20
  },
  {
    "left_category": "college_ohio_st",
    "right_category": "decade_20s",
    "left_label": "Went to Ohio State",
    "right_label": "Played in 2020s",
    "valid_players": [
      "Aaliyah Patty",
      "Ava Watson",
      "Braxtin Miller",
      "Bryn Martin",
      "Chance Gray",
      "Cotie McMahon",
      "Dorka Juhasz",
      "Eboni Walker",
      "Elsa Lemmila",
      "Hevynne Bristow",
      "Jacy Sheldon",
      "Jaloni Cambridge",
      "Janai Crooms",
      "Kateri Poole",
      "Kennedy Cambridge",
      "Kylee Kitts",
      "Madison Greene",
      "Rebeka Mikulasikova",
      "Rikki Harris",
      "Taylor Thierry"
    ],
    "answer_count": 20
  },
  {
    "left_category": "decade_20s",
    "right_category": "college_unc",
    "left_label": "Played in 2020s",
    "right_label": "Went to UNC",
    "valid_players": [
      "Alexandra Zelaya",
      "Alyssa Ustby",
      "Anya Poole",
      "Blanca Thomas",
      "Ciera Toomey",
      "Deja Kelly",
      "Destinee Walker",
      "Elina Aarnisalo",
      "Emily Sullivan",
      "Indya Nivar",
      "Jaelynn Murray",
      "Janelle Bailey",
      "Jocelyn Jones",
      "Kennedy Todd-Williams",
      "Laila Hull",
      "Lanie Grant",
      "Leah Church",
      "Malu Tshitenge",
      "Nyla Brooks",
      "Olivia Smith",
      "Paulina Paris",
      "Reniya Kelly",
      "Shayla Bennett",
      "Stephanie Watts",
      "Taliyah Henderson",
      "Taylor Koenen"
    ],
    "answer_count": 26
  },
  {
    "left_category": "college_unc",
    "right_category": "decade_10s",
    "left_label": "Went to UNC",
    "right_label": "Played in 2010s",
    "valid_players": [
      "Allisha Gray",
      "Alyssa Okoene",
      "Brittany Rountree",
      "Danielle Butts",
      "Destinee Walker",
      "Emily Sullivan",
      "Erika Johnson",
      "Hillary Fuller",
      "Hillary Summers",
      "Jaelynn Murray",
      "Jamie Cherry",
      "Janelle Bailey",
      "Jessica Washington",
      "Jocelyn Jones",
      "Latifah Coleman",
      "Leah Church",
      "N'Dea Bryant",
      "Olivia Smith",
      "Paris Kea",
      "Shayla Bennett",
      "Stephanie Mavunga",
      "Stephanie Watts",
      "Taylor Koenen",
      "Xylina McDaniel"
    ],
    "answer_count": 24
  },
  {
    "left_category": "decade_10s",
    "right_category": "ncaaw_20ppg",
    "left_label": "Played in 2010s",
    "right_label": "20+ PPG in College (W)",
    "valid_players": [
      "Brittney Griner",
      "Camille Zimmerman",
      "Chelsea Welch",
      "Chennedy Carter",
      "Chiney Ogwumike",
      "Chrishae Rowe",
      "Courtney Williams",
      "Dearica Hamby",
      "Dezz Ramos",
      "Elena Delle Donne",
      "Jennie Simms",
      "Jessica Kovatch",
      "Jordan Hooper",
      "Katelynn Flaherty",
      "Ke'Shunan James",
      "Kelsey Mitchell",
      "Kelsey Plum",
      "Kristine Anigwe",
      "Larissa Lurken",
      "Lizzy Wendell",
      "Maggie Lucas",
      "Megan Gustafson",
      "Mikayla Ferenz",
      "Natasha Howard",
      "Odyssey Sims",
      "Precious Hall",
      "Rachel Banham",
      "Randi Brown",
      "Rhyne Howard"
    ],
    "answer_count": 29
  },
  {
    "left_category": "ncaaw_20ppg",
    "right_category": "ncaaw_aa",
    "left_label": "20+ PPG in College (W)",
    "right_label": "College All-American (W)",
    "valid_players": [
      "Brittney Griner",
      "Caitlin Clark",
      "Chamique Holdsclaw",
      "Cheryl Miller",
      "Elena Delle Donne",
      "Lisa Leslie",
      "Sheryl Swoopes"
    ],
    "answer_count": 7
  },
  {
    "left_category": "ncaaw_aa",
    "right_category": "ncaaw_tennessee",
    "left_label": "College All-American (W)",
    "right_label": "Played at Tennessee (W)",
    "valid_players": [
      "Candace Parker",
      "Chamique Holdsclaw",
      "Tamika Catchings"
    ],
    "answer_count": 3
  },
  {
    "left_category": "ncaaw_tennessee",
    "right_category": "decade_10s",
    "left_label": "Played at Tennessee (W)",
    "right_label": "Played in 2010s",
    "valid_players": [
      "Alexa Middleton",
      "Andraya Carter",
      "Ariel Massengale",
      "Bashaara Graves",
      "Cheridene Green",
      "Cierra Burdick",
      "Diamond DeShields",
      "Evina Westbrook",
      "Isabelle Harrison",
      "Jaime Nared",
      "Jasmine Jones",
      "Jazmine Massengill",
      "Jordan Reynolds",
      "Jordan Walker",
      "Kasiyahna Kushkituah",
      "Kortney Dunbar",
      "MeMe Jackson",
      "Meighan Simmons",
      "Mercedes Russell",
      "Nia Moore",
      "Rae Burrell",
      "Rennia Davis",
      "Schaquilla Nunn",
      "Te'a Cooper"
    ],
    "answer_count": 24
  },
  {
    "left_category": "decade_10s",
    "right_category": "college_michigan",
    "left_label": "Played in 2010s",
    "right_label": "Went to Michigan",
    "valid_players": [
      "Akienreh Johnson",
      "Amy Dilk",
      "Cyesha Damian Goree",
      "Danielle Rauch",
      "Danielle Williams",
      "Emily Kiser",
      "Hailey Brown",
      "Hallie Thome",
      "Jillian Dunston",
      "Katelynn Flaherty",
      "Kayla Robbins",
      "KeAsja Peace",
      "Kelsey Mitchell",
      "Leigha Brown",
      "Madison Ristovski",
      "Naz Hillmon",
      "Nicole Elmblad",
      "Nicole Munger",
      "Shannon Smith",
      "Siera Thompson",
      "Val Driscoll"
    ],
    "answer_count": 21
  },
  {
    "left_category": "college_michigan",
    "right_category": "decade_20s",
    "left_label": "Went to Michigan",
    "right_label": "Played in 2020s",
    "valid_players": [
      "Akienreh Johnson",
      "Alyssa Crockett",
      "Amy Dilk",
      "Brooke Quarles-Daniels",
      "Cameron Williams",
      "Chyra Evans",
      "Danielle Rauch",
      "Elise Stuck",
      "Emily Kiser",
      "Greta Kampschroeder",
      "Hailey Brown",
      "Izabel Varejao",
      "Jordan Hobbs",
      "Kayla Robbins",
      "KeAsja Peace",
      "Laila Phelia",
      "Leigha Brown",
      "Macy Brown",
      "Maddie Nolan",
      "Michelle Sidor",
      "Mila Holloway",
      "Naz Hillmon",
      "Olivia Olson",
      "Syla Swords",
      "Taylor Woodson",
      "Te'Yala Delfosse",
      "Yulia Grabovskaia"
    ],
    "answer_count": 27
  },
  {
    "left_category": "decade_20s",
    "right_category": "ncaaw_iowa",
    "left_label": "Played in 2020s",
    "right_label": "Played at Iowa (W)",
    "valid_players": [
      "AJ Ediger",
      "Addie Deal",
      "Addison O'Grady",
      "Alexis Sevillian",
      "Amanda Ollinger",
      "Ava Heiden",
      "Caitlin Clark",
      "Gabbie Marshall",
      "Hannah Stuelke",
      "Journey Houston",
      "Kate Martin",
      "Kathleen Doyle",
      "Kylie Feuerbach",
      "Layla Hays",
      "Logan Cook",
      "Makenzie Meyer",
      "McKenna Warnock",
      "Monika Czinano",
      "Sharon Goodman",
      "Sydney Affolter",
      "Taylor McCabe",
      "Taylor Stremlow",
      "Teagan Mallegni",
      "Tomi Taiwo"
    ],
    "answer_count": 24
  }
]