[
  {
    "left_category": "mlb_2000hits",
    "right_category": "mlb_400hr",
    "left_label": "2,000+ Career Hits",
    "right_label": "400+ Career HRs",
    "valid_players": [
      "Adrian Beltre",
      "Albert Pujols",
      "Alex Rodriguez",
      "Alfonso Soriano",
      "Andre Dawson",
      "Babe Ruth",
      "Barry Bonds",
      "Billy Williams",
      "Cal Ripken",
      "Carl Yastrzemski",
      "Carlos Beltran",
      "Carlos Delgado",
      "Chipper Jones",
      "Darrell Evans",
      "Dave Winfield",
      "David Ortiz",
      "Duke Snider",
      "Eddie Mathews",
      "Eddie Murray",
      "Ernie Banks",
      "Frank Robinson",
      "Frank Thomas",
      "Fred McGriff",
      "Gary Sheffield",
      "Hank Aaron",
      "Harmon Killebrew",
      "Jason Giambi",
      "Jeff Bagwell",
      "Jim Thome",
      "Jimmie Foxx",
      "Ken Griffey",
      "Lou Gehrig",
      "Manny Ramirez",
      "Mel Ott",
      "Mickey Mantle",
      "Miguel Cabrera",
      "Mike Piazza",
      "Mike Schmidt",
      "Paul Konerko",
      "Rafael Palmeiro",
      "Reggie Jackson",
      "Sammy Sosa",
      "Stan Musial",
      "Ted Williams",
      "Vladimir Guerrero",
      "Willie Mays",
      "Willie McCovey",
      "Willie Stargell"
    ],
    "answer_count": 48
  },
  {
    "left_category": "mlb_400hr",
    "right_category": "mlb_mvp",
    "left_label": "400+ Career HRs",
    "right_label": "MLB MVP",
    "valid_players": [
      "Albert Pujols",
      "Alex Rodriguez",
      "Andre Dawson",
      "Babe Ruth",
      "Barry Bonds",
      "Cal Ripken",
      "Carl Yastrzemski",
      "Chipper Jones",
      "Ernie Banks",
      "Frank Robinson",
      "Frank Thomas",
      "Hank Aaron",
      "Harmon Killebrew",
      "Jason Giambi",
      "Jeff Bagwell",
      "Jimmie Foxx",
      "Jose Canseco",
      "Juan Gonzalez",
      "Ken Griffey",
      "Lou Gehrig",
      "Mickey Mantle",
      "Miguel Cabrera",
      "Mike Schmidt",
      "Reggie Jackson",
      "Sammy Sosa",
      "Stan Musial",
      "Ted Williams",
      "Vladimir Guerrero",
      "Willie Mays",
      "Willie McCovey",
      "Willie Stargell"
    ],
    "answer_count": 31
  },
  {
    "left_category": "mlb_mvp",
    "right_category": "mlb_1000rbi",
    "left_label": "MLB MVP",
    "right_label": "1,000+ Career RBI",
    "valid_players": [
      "Albert Pujols",
      "Alex Rodriguez",
      "Andre Dawson",
      "Babe Ruth",
      "Barry Bonds",
      "Bob Elliott",
      "Boog Powell",
      "Brooks Robinson",
      "Cal Ripken",
      "Carl Yastrzemski",
      "Charlie Gehringer",
      "Chipper Jones",
      "Chuck Klein",
      "Dale Murphy",
      "Dave Parker",
      "Dick Allen",
      "Don Baylor",
      "Don Mattingly",
      "Eddie Collins",
      "Ernie Banks",
      "Frank Robinson",
      "Frank Thomas",
      "Frankie Frisch",
      "Fred Lynn",
      "Gabby Hartnett",
      "George Bell",
      "George Brett",
      "George Foster",
      "George Sisler",
      "Hank Aaron",
      "Hank Greenberg",
      "Harmon Killebrew",
      "Ivan Rodriguez",
      "Jason Giambi",
      "Jeff Bagwell",
      "Jeff Kent",
      "Jim Bottomley",
      "Jim Rice",
      "Jimmie Foxx",
      "Joe DiMaggio",
      "Joe Medwick",
      "Joe Morgan",
      "Joe Torre",
      "Joey Votto",
      "Johnny Bench",
      "Jose Canseco",
      "Juan Gonzalez",
      "Keith Hernandez",
      "Ken Boyer",
      "Ken Griffey",
      "Larry Walker",
      "Lou Gehrig",
      "Mickey Mantle",
      "Miguel Cabrera",
      "Miguel Tejada",
      "Mike Schmidt",
      "Mo Vaughn",
      "Orlando Cepeda",
      "Paul Waner",
      "Pete Rose",
      "Reggie Jackson",
      "Rickey Henderson",
      "Roberto Clemente",
      "Robin Yount",
      "Rod Carew",
      "Rogers Hornsby",
      "Ryan Braun",
      "Ryan Howard",
      "Ryne Sandberg",
      "Sammy Sosa",
      "Stan Musial",
      "Steve Garvey",
      "Ted Williams",
      "Tris Speaker",
      "Ty Cobb",
      "Vladimir Guerrero",
      "Willie Mays",
      "Willie McCovey",
      "Willie Stargell",
      "Yogi Berra"
    ],
    "answer_count": 80
  },
  {
    "left_category": "mlb_1000rbi",
    "right_category": "decade_00s",
    "left_label": "1,000+ Career RBI",
    "right_label": "Played in 2000s",
    "valid_players": [
      "Adam Dunn",
      "Adrian Beltre",
      "Adrian Gonzalez",
      "Albert Belle",
      "Albert Pujols",
      "Alex Rodriguez",
      "Alfonso Soriano",
      "Andres Galarraga",
      "Andruw Jones",
      "Aramis Ramirez",
      "B. J. Surhoff",
      "Barry Bonds",
      "Bernie Williams",
      "Bobby Abreu",
      "Bobby Bonilla",
      "Bret Boone",
      "Brian Giles",
      "Brian McCann",
      "Cal Ripken",
      "Carlos Beltran",
      "Carlos Delgado",
      "Carlos Lee",
      "Chase Utley",
      "Chipper Jones",
      "Craig Biggio",
      "Dante Bichette",
      "David Justice",
      "David Ortiz",
      "Derek Jeter",
      "Derrek Lee",
      "Edgar Martinez",
      "Edwin Encarnacion",
      "Ellis Burks",
      "Eric Karros",
      "Evan Longoria",
      "Frank Thomas",
      "Fred McGriff",
      "Garret Anderson",
      "Gary Gaetti",
      "Gary Sheffield",
      "Greg Vaughn",
      "Harold Baines",
      "Ivan Rodriguez",
      "Jason Giambi",
      "Jeff Bagwell",
      "Jeff Conine",
      "Jeff Kent",
      "Jermaine Dye",
      "Jim Edmonds",
      "Jim Thome",
      "Joey Votto",
      "John Olerud",
      "Johnny Damon",
      "Jorge Posada",
      "Jose Canseco",
      "Juan Gonzalez",
      "Julio Franco",
      "Justin Upton",
      "Ken Griffey",
      "Lance Berkman",
      "Larry Walker",
      "Luis Gonzalez",
      "Magglio Ordonez",
      "Manny Ramirez",
      "Mark Grace",
      "Mark McGwire",
      "Mark Teixeira",
      "Matt Holliday",
      "Matt Kemp",
      "Matt Williams",
      "Michael Young",
      "Miguel Cabrera",
      "Miguel Tejada",
      "Mike Piazza",
      "Mo Vaughn",
      "Moises Alou",
      "Nelson Cruz",
      "Nick Markakis",
      "Paul Konerko",
      "Paul O'Neill",
      "Prince Fielder",
      "Rafael Palmeiro",
      "Raul Ibanez",
      "Rickey Henderson",
      "Roberto Alomar",
      "Robin Ventura",
      "Robinson Cano",
      "Ron Gant",
      "Ruben Sierra",
      "Ryan Braun",
      "Ryan Howard",
      "Ryan Zimmerman",
      "Sammy Sosa",
      "Scott Rolen",
      "Shawn Green",
      "Steve Finley",
      "Tim Salmon",
      "Tino Martinez",
      "Todd Helton",
      "Todd Zeile",
      "Tony Gwynn",
      "Torii Hunter",
      "Travis Fryman",
      "Victor Martinez",
      "Vinny Castilla",
      "Vladimir Guerrero",
      "Wally Joyner",
      "Will Clark"
    ],
    "answer_count": 108
  },
  {
    "left_category": "decade_00s",
    "right_category": "ncaaf_rush3k",
    "left_label": "Played in 2000s",
    "right_label": "3,000+ College Rush Yds",
    "valid_players": [
      "Alexander Robinson",
      "Alfred Morris",
      "Andre Ellington",
      "Anthony Allen",
      "Asher Clark",
      "Ben Tate",
      "Bernard Pierce",
      "Brandon West",
      "Bryce Beall",
      "C.J. Spiller",
      "Charles Sims",
      "Chris Polk",
      "Colin Kaepernick",
      "Cyrus Gray",
      "Damion Fletcher",
      "Daniel Porter",
      "DeMarco Murray",
      "Delone Carter",
      "Denard Robinson",
      "Doug Martin",
      "Eugene Jarvis",
      "Evan Royster",
      "Harvey Unga",
      "Isaiah Pead",
      "Jacquizz Rodgers",
      "James Starks",
      "John Clay",
      "Johnathan Franklin",
      "Jonathan Dwyer",
      "Jordan Todman",
      "Kasey Carrier",
      "Kendall Hunter",
      "Kenjon Barner",
      "Lance Dunbar",
      "Mark Ingram",
      "MiQuale Lewis",
      "Montee Ball",
      "Montel Harris",
      "Noel Devine",
      "Ray Graham",
      "Reggie Arnold",
      "Rex Burkhead",
      "Robbie Rouse",
      "Robert Turbin",
      "Rodney Stewart",
      "Roy Helu Jr.",
      "Ryan Mathews",
      "Stepfan Taylor",
      "Toby Gerhart",
      "Trent Richardson",
      "Trent Steelman",
      "Vai Taua",
      "Zac Stacy",
      "Zach Line"
    ],
    "answer_count": 54
  },
  {
    "left_category": "ncaaf_rush3k",
    "right_category": "college_lsu",
    "left_label": "3,000+ College Rush Yds",
    "right_label": "Went to LSU",
    "valid_players": [
      "Derrius Guice",
      "Leonard Fournette"
    ],
    "answer_count": 2
  },
  {
    "left_category": "college_lsu",
    "right_category": "pos_nfl_ol",
    "left_label": "Went to LSU",
    "right_label": "NFL Offensive Lineman",
    "valid_players": [
      "Andrew Whitworth",
      "Jerald Hawkins"
    ],
    "answer_count": 2
  },
  {
    "left_category": "pos_nfl_ol",
    "right_category": "team_steelers",
    "left_label": "NFL Offensive Lineman",
    "right_label": "Steelers",
    "valid_players": [
      "Alejandro Villanueva",
      "Jerald Hawkins",
      "Jim Sweeney",
      "Maurkice Pouncey"
    ],
    "answer_count": 4
  },
  {
    "left_category": "team_steelers",
    "right_category": "team_49ers",
    "left_label": "Steelers",
    "right_label": "49ers",
    "valid_players": [
      "Allen Rossum",
      "Arnaz Battle",
      "Cedrick Wilson",
      "Emmanuel Sanders",
      "Ray-Ray McCloud",
      "Vance McDonald"
    ],
    "answer_count": 6
  },
  {
    "left_category": "team_49ers",
    "right_category": "team_bills",
    "left_label": "49ers",
    "right_label": "Bills",
    "valid_players": [
      "Anthony Dixon",
      "Emmanuel Sanders",
      "Frank Gore",
      "Jeremy Kerley",
      "Jordan Matthews",
      "Marquise Goodwin",
      "Matt Breida",
      "Nate Clements",
      "Ray-Ray McCloud",
      "Reggie Bush",
      "Terrell Owens",
      "Trent Sherfield",
      "Tyler Kroft"
    ],
    "answer_count": 13
  },
  {
    "left_category": "team_bills",
    "right_category": "college_ohio_st",
    "left_label": "Bills",
    "right_label": "Went to Ohio State",
    "valid_players": [
      "Cardale Jones",
      "Nate Clements",
      "Reggie Germany",
      "Terrelle Pryor"
    ],
    "answer_count": 4
  },
  {
    "left_category": "college_ohio_st",
    "right_category": "ncaaf_ohio_st",
    "left_label": "Went to Ohio State",
    "right_label": "Played at Ohio State (CFB)",
    "valid_players": [
      "A.J. Alexander",
      "Aaron Cox",
      "Aaron Pettrey",
      "Adam Homan",
      "Adolphus Washington",
      "Alex Stump",
      "Alex Williams",
      "Amari McMahon",
      "Amir Riep",
      "Anderson Russell",
      "Andre Amos",
      "Andrew Sweat",
      "Antwuan Jackson",
      "Armani Reeves",
      "Austin Mack",
      "Austin Spitler",
      "Baron Browning",
      "Ben Buchanan",
      "Ben Schmiesing",
      "Billy Price",
      "Binjimen Victor",
      "Blake Haubeil",
      "Bo DeLande",
      "Bradley Roby",
      "Brandon Inniss",
      "Brandon Saine",
      "Braxton Miller",
      "Brendon White",
      "Bri'onte Dunn",
      "Brian Rolle",
      "Bryce Prater",
      "Bryson Shaw",
      "C.J. Barnett",
      "C.J. Hicks",
      "C.J. Saunders",
      "C.J. Stroud",
      "Cade Kacherski",
      "Cade Stover",
      "Caden Curry",
      "Calvin Simpson-Hunt",
      "Cameron Brown",
      "Cameron Heyward",
      "Cameron Johnston",
      "Cameron Martinez",
      "Cardale Jones",
      "Carlos Hyde",
      "Carnell Tate",
      "Cayden Saunders",
      "Chase Young",
      "Chimdi Chekwa",
      "Chris Booker",
      "Chris Fields",
      "Chris Olave",
      "Chris Worley",
      "Christian Bryant",
      "Cody Simon",
      "Corey Brown",
      "Corey Smith",
      "Craig Fada",
      "Craig Young",
      "Curtis Grant",
      "Curtis Samuel",
      "Dallan Hayden",
      "Dallas Gant",
      "Damon Arnette",
      "Damon Webb",
      "Dane Sanzenbacher",
      "Daniel Herron",
      "Dante Booker",
      "Darron Lee",
      "Davison Igbinosun",
      "Davon Hamilton",
      "DeVier Posey",
      "DeaMonte Trayanum",
      "Demario McCall",
      "Denzel Burke",
      "Denzel Ward",
      "Devin Barclay",
      "Devin Brown",
      "Devin Smith",
      "Devon Torrence",
      "Devonte Butler",
      "Dominic Clarke",
      "Dominic DiMaccio",
      "Donovan Jackson",
      "Dontre Wilson",
      "Doran Grant",
      "Doug Worthington",
      "Dre'Mont Jones",
      "Drew Basil",
      "Drue Chrisman",
      "Duron Carter",
      "Dwayne Haskins",
      "Dylan Thompson",
      "Eli Apple",
      "Elijaah Goins",
      "Ellijah Gardiner",
      "Emeka Egbuka",
      "Eric Glover-Williams",
      "Erick Smith",
      "Etienne Sabino",
      "Evan Pryor",
      "Evan Spencer",
      "Ezekiel Elliott",
      "Gabe Powers",
      "Gareon Conley",
      "Garrett Hummel",
      "Garrett Wilson",
      "Garyn Prater",
      "Gee Scott Jr.",
      "Grant Schwartz",
      "Gunnar Hoak",
      "Haskell Garrett",
      "Hero Kanu",
      "Isaiah Prince",
      "Isaiah Pryor",
      "J.K. Dobbins",
      "J.T. Barrett",
      "J.T. Tuimoloau",
      "JK Johnson",
      "Jaamal Berry",
      "Jack Miller III",
      "Jack Sawyer",
      "Jack Willoughby",
      "Jaden McKenzie",
      "Jahsen Wint",
      "Jakailin Johnson",
      "Jake Ballard",
      "Jake Hausmann",
      "Jake Seibert",
      "Jake Stoneburner",
      "Jalin Marshall",
      "Jalyn Holmes",
      "Jamarco Jones",
      "Jared Drake",
      "Jashon Cornell",
      "Javontae Jean-Baptiste",
      "Jaxon Smith-Njigba",
      "Jayden Ballard",
      "Jayden Fielding",
      "Jaylen Harris",
      "Jaylen Johnson",
      "Jeff Greene",
      "Jeff Heuerman",
      "Jeffie Johnson",
      "Jeffrey Okudah",
      "Jelani Thurman",
      "Jeremy Ruckert",
      "Jermaine Mathews Jr.",
      "Jermale Hines",
      "Jermil Martin",
      "Jerome Baker",
      "Jerron Cage",
      "Jesse Mirco",
      "Joe Bauserman",
      "Joe Burger",
      "Joe Gantz",
      "Joe Royer",
      "Joey Bosa",
      "Johnnie Dixon",
      "Jonathan Newsome",
      "Jonathon Cooper",
      "Joop Mitchell",
      "Jordan Fuller",
      "Jordan Hall",
      "Jordan Hancock",
      "Jordan Leasure",
      "Josh Proctor",
      "Joshua Alabi",
      "Joshua Perry",
      "Julian Fleming",
      "Justin Fields",
      "Justin Hilliard",
      "Jyaire Brown",
      "K'Vaughan Pope",
      "K.C. Christian",
      "K.J. Hill",
      "Kamryn Babb",
      "Kato Mitchell",
      "Kayden McDonald",
      "Keandre Jones",
      "Kendall Sheffield",
      "Kenny Guiton",
      "Kenyatta Jackson",
      "Kevin Dever",
      "Kourt Williams",
      "Kurt Coleman",
      "Kye Stokes",
      "Kyion Grayes",
      "Kyle Clinton",
      "Kyle McCord",
      "Lathan Ransom",
      "Lawrence Wilson",
      "Lejond Cavazos",
      "Lincoln Kienholz",
      "Luke Farrell",
      "Malcolm Pridgeon",
      "Malik Harrison",
      "Malik Hartford",
      "Malik Hooker",
      "Marcus Baugh",
      "Marcus Crowley",
      "Marcus Hooker",
      "Marcus Williams",
      "Marcus Williamson",
      "Marshon Lattimore",
      "Marvin Harrison Jr.",
      "Master Teague",
      "Matthew Jones",
      "Michael Hill",
      "Michael Thomas",
      "Mike Hall",
      "Mike Weber",
      "Mitch Rossi",
      "Mitchell Melton",
      "Miyan Williams",
      "Nathan Williams",
      "Nick Bosa",
      "Nick Conner",
      "Nick Seme",
      "Nick Vannett",
      "Noah Brown",
      "Noah Potter",
      "Omari Abor",
      "Orhian Johnson",
      "Parris Campbell",
      "Patrick Gurd",
      "Pete Werner",
      "Raekwon McMillan",
      "Rashod Berry",
      "Ray Small",
      "Reid Carrico",
      "Reid Fragel",
      "Reis Stocksdale",
      "Ricky Crawford",
      "Robert Cope",
      "Robert Landers",
      "Rod Smith",
      "Ron Tanner",
      "Ronnie Hickman",
      "Ross Homan",
      "Ryan Batsch",
      "Ryan Shazier",
      "Ryan Turner",
      "Ryan Watts",
      "Sam Hubbard",
      "Sean Nuernberger",
      "Sevyn Banks",
      "Shaun Wade",
      "Solomon Thomas",
      "Sonny Styles",
      "Spencer Smith",
      "Steele Chambers",
      "Steve Miller",
      "Storm Klein",
      "T.Y. Williams",
      "TC Caffey",
      "Taron Vincent",
      "Tate Martell",
      "Taurian Washington",
      "Teradja Mitchell",
      "Terry McLaurin",
      "Thaddeus Gibson",
      "Thayer Munford",
      "Todd Denlinger",
      "Tommy Eichenberg",
      "Tommy Togiai",
      "Tony Jackson",
      "Torrell Williams",
      "Tracy Sprinkle",
      "Travis Howard",
      "Trayvon Wilburn",
      "TreVeyon Henderson",
      "Tuf Borland",
      "Ty Hamilton",
      "Tyleik Williams",
      "Tyler Durbin",
      "Tyler Friday",
      "Tyler Moeller",
      "Tyquan Lewis",
      "Tyreke Johnson",
      "Tyreke Smith",
      "Tyvis Powell",
      "Verlon Reed",
      "Vonn Bell",
      "Wyatt Davis",
      "Xavier Johnson",
      "Zach Boren",
      "Zach Domicone",
      "Zach Harrison",
      "Zach Hoover",
      "Zach Turnure",
      "Zaid Hamdan"
    ],
    "answer_count": 293
  },
  {
    "left_category": "ncaaf_ohio_st",
    "right_category": "decade_10s",
    "left_label": "Played at Ohio State (CFB)",
    "right_label": "Played in 2010s",
    "valid_players": [
      "A.J. Alexander",
      "Aaron Cox",
      "Adam Homan",
      "Adolphus Washington",
      "Alex Stump",
      "Alex Williams",
      "Amari McMahon",
      "Amir Riep",
      "Andrew Sweat",
      "Antwuan Jackson",
      "Armani Reeves",
      "Austin Mack",
      "Baron Browning",
      "Ben Buchanan",
      "Ben Schmiesing",
      "Billy Price",
      "Binjimen Victor",
      "Blake Haubeil",
      "Bo DeLande",
      "Bradley Roby",
      "Brandon Saine",
      "Braxton Miller",
      "Brendon White",
      "Bri'onte Dunn",
      "Brian Rolle",
      "Bryson Shaw",
      "C.J. Barnett",
      "C.J. Saunders",
      "Cade Stover",
      "Cameron Brown",
      "Cameron Heyward",
      "Cameron Johnston",
      "Cardale Jones",
      "Carlos Hyde",
      "Chase Young",
      "Chimdi Chekwa",
      "Chris Fields",
      "Chris Olave",
      "Chris Worley",
      "Christian Bryant",
      "Corey Brown",
      "Corey Smith",
      "Craig Fada",
      "Craig Young",
      "Curtis Grant",
      "Curtis Samuel",
      "Dallas Gant",
      "Damon Arnette",
      "Damon Webb",
      "Dane Sanzenbacher",
      "Daniel Herron",
      "Dante Booker",
      "Darron Lee",
      "Davon Hamilton",
      "DeVier Posey",
      "Demario McCall",
      "Denzel Ward",
      "Devin Barclay",
      "Devin Smith",
      "Devon Torrence",
      "Devonte Butler",
      "Dominic Clarke",
      "Dominic DiMaccio",
      "Dontre Wilson",
      "Doran Grant",
      "Dre'Mont Jones",
      "Drew Basil",
      "Drue Chrisman",
      "Dwayne Haskins",
      "Dylan Thompson",
      "Eli Apple",
      "Elijaah Goins",
      "Ellijah Gardiner",
      "Eric Glover-Williams",
      "Erick Smith",
      "Etienne Sabino",
      "Evan Spencer",
      "Ezekiel Elliott",
      "Gareon Conley",
      "Garrett Hummel",
      "Garrett Wilson",
      "Garyn Prater",
      "Grant Schwartz",
      "Gunnar Hoak",
      "Haskell Garrett",
      "Isaiah Prince",
      "Isaiah Pryor",
      "J.K. Dobbins",
      "J.T. Barrett",
      "Jaamal Berry",
      "Jack Willoughby",
      "Jahsen Wint",
      "Jake Hausmann",
      "Jake Stoneburner",
      "Jalin Marshall",
      "Jalyn Holmes",
      "Jamarco Jones",
      "Jared Drake",
      "Jashon Cornell",
      "Javontae Jean-Baptiste",
      "Jaylen Harris",
      "Jeff Greene",
      "Jeff Heuerman",
      "Jeffie Johnson",
      "Jeffrey Okudah",
      "Jeremy Ruckert",
      "Jermale Hines",
      "Jerome Baker",
      "Jerron Cage",
      "Joe Bauserman",
      "Joe Burger",
      "Joey Bosa",
      "Johnnie Dixon",
      "Jonathan Newsome",
      "Jonathon Cooper",
      "Jordan Fuller",
      "Jordan Hall",
      "Jordan Leasure",
      "Josh Proctor",
      "Joshua Alabi",
      "Joshua Perry",
      "Justin Fields",
      "Justin Hilliard",
      "K'Vaughan Pope",
      "K.J. Hill",
      "Kato Mitchell",
      "Keandre Jones",
      "Kendall Sheffield",
      "Kenny Guiton",
      "Kevin Dever",
      "Kyle Clinton",
      "Luke Farrell",
      "Malcolm Pridgeon",
      "Malik Harrison",
      "Malik Hooker",
      "Marcus Baugh",
      "Marcus Crowley",
      "Marcus Hooker",
      "Marcus Williamson",
      "Marshon Lattimore",
      "Master Teague",
      "Michael Hill",
      "Michael Thomas",
      "Mike Weber",
      "Mitch Rossi",
      "Nathan Williams",
      "Nick Bosa",
      "Nick Conner",
      "Nick Seme",
      "Nick Vannett",
      "Noah Brown",
      "Noah Potter",
      "Orhian Johnson",
      "Parris Campbell",
      "Pete Werner",
      "Raekwon McMillan",
      "Rashod Berry",
      "Reid Fragel",
      "Ricky Crawford",
      "Robert Landers",
      "Rod Smith",
      "Ron Tanner",
      "Ross Homan",
      "Ryan Shazier",
      "Sam Hubbard",
      "Sean Nuernberger",
      "Sevyn Banks",
      "Shaun Wade",
      "Solomon Thomas",
      "Spencer Smith",
      "Steele Chambers",
      "Steve Miller",
      "Storm Klein",
      "T.Y. Williams",
      "Taron Vincent",
      "Tate Martell",
      "Taurian Washington",
      "Teradja Mitchell",
      "Terry McLaurin",
      "Tommy Togiai",
      "Tony Jackson",
      "Tracy Sprinkle",
      "Travis Howard",
      "Tuf Borland",
      "Tyler Durbin",
      "Tyler Friday",
      "Tyler Moeller",
      "Tyquan Lewis",
      "Tyreke Johnson",
      "Tyreke Smith",
      "Tyvis Powell",
      "Verlon Reed",
      "Vonn Bell",
      "Xavier Johnson",
      "Zach Boren",
      "Zach Domicone",
      "Zach Harrison",
      "Zach Turnure",
      "Zaid Hamdan"
    ],
    "answer_count": 199
  },
  {
    "left_category": "decade_10s",
    "right_category": "team_giants",
    "left_label": "Played in 2010s",
    "right_label": "Giants",
    "valid_players": [
      "Adrien Robinson",
      "Ahmad Bradshaw",
      "Alex Tanney",
      "Alfred Morris",
      "Andre Brown",
      "Andre Williams",
      "Bear Pascoe",
      "Ben Edwards",
      "Bennie Fowler",
      "Bobby Rainey",
      "Brandon Jacobs",
      "Brandon Marshall",
      "Brandon Myers",
      "Brandon Stokley",
      "C.J. Board",
      "Cody Core",
      "Cody Latimer",
      "Colt McCoy",
      "Cooper Taylor",
      "Corey Coleman",
      "Corey Washington",
      "Curtis Painter",
      "D.J. Ware",
      "Da'Mari Scott",
      "Da'Rel Scott",
      "Daniel Fells",
      "Daniel Jones",
      "Dante Pettis",
      "Darcy Johnson",
      "Darius Powe",
      "Darius Slayton",
      "Darren Waller",
      "David Carr",
      "David Wilson",
      "Deon Yelder",
      "Derek Hagan",
      "Derrick Ward",
      "Devin Thomas",
      "Devontae Booker",
      "Dion Lewis",
      "Domenik Hixon",
      "Duke Calhoun",
      "Dwayne Harris",
      "Ed Eagan",
      "Eli Manning",
      "Elijhaa Penny",
      "Ereck Flowers",
      "Evan Engram",
      "Gartrell Johnson",
      "Geno Smith",
      "Geremy Davis",
      "Golden Tate",
      "Gunner Olszewski",
      "Hakeem Nicks",
      "Hakeem Valles",
      "Henry Hynoski",
      "Hunter Sharp",
      "Jake Ballard",
      "James Washington",
      "Janoris Jenkins",
      "Javorius Allen",
      "Jawill Davis",
      "Jerell Adams",
      "Jeremy Shockey",
      "Jerome Cunningham",
      "Jerrel Jernigan",
      "John Conner",
      "John Ross",
      "Jon Hilliman",
      "Jonathan Stewart",
      "Julian Talley",
      "Kaden Smith",
      "Kalif Raymond",
      "Kenny Golladay",
      "Kerry Collins",
      "Kevin Boss",
      "Kevin Ogletree",
      "Kyle Lauletta",
      "Kyle Rudolph",
      "Larry Donnell",
      "Levine Toilolo",
      "Louis Murphy",
      "Madison Hedgecock",
      "Marcus Johnson",
      "Mario Manningham",
      "Marquis Bundy",
      "Martellus Bennett",
      "Matt Breida",
      "Matt Dodge",
      "Matt LaCosse",
      "Michael Clayton",
      "Michael Cox",
      "Mike Glennon",
      "Myles White",
      "Nat Berhe",
      "Nick Vannett",
      "Odell Beckham Jr.",
      "Orleans Darkwa",
      "Parris Campbell",
      "Paul Perkins",
      "Peyton Hillis",
      "Pharoh Cooper",
      "Plaxico Burress",
      "Preston Parker",
      "Ramses Barden",
      "Rashad Jennings",
      "Rhett Ellison",
      "Richie James",
      "Riley Dixon",
      "Roger Lewis",
      "Rueben Randle",
      "Russell Shepard",
      "Ryan Nassib",
      "Sage Rosenfels",
      "Saquon Barkley",
      "Scott Simonson",
      "Shane Vereen",
      "Spencer Pulley",
      "Stacy Coley",
      "Sterling Shepard",
      "Steve Smith",
      "Steve Weatherford",
      "T.J. Jones",
      "Tavarres King",
      "Travis Beckum",
      "Travis Rudolph",
      "Tyrod Taylor",
      "Victor Cruz",
      "Visanthe Shiancoe",
      "Wayne Gallman",
      "Will Tye",
      "William Beatty"
    ],
    "answer_count": 132
  },
  {
    "left_category": "team_giants",
    "right_category": "team_titans",
    "left_label": "Giants",
    "right_label": "Titans",
    "valid_players": [
      "Alex Tanney",
      "C.J. Board",
      "Derek Hagan",
      "Dion Lewis",
      "Greg Comella",
      "Kalif Raymond",
      "Kerry Collins",
      "Marcus Johnson",
      "Visanthe Shiancoe"
    ],
    "answer_count": 9
  },
  {
    "left_category": "team_titans",
    "right_category": "pos_rb",
    "left_label": "Titans",
    "right_label": "Running Back",
    "valid_players": [
      "Ahmard Hall",
      "Antonio Andrews",
      "Antowain Smith",
      "Bishop Sankey",
      "Casey Cramer",
      "Chris Barclay",
      "Chris Brown",
      "Chris Henry",
      "Chris Johnson",
      "Collin Mooney",
      "D'Onta Foreman",
      "Dalyn Dawkins",
      "Damien Nash",
      "Darius Reynaud",
      "Darrynton Evans",
      "David Cobb",
      "David Fluellen",
      "DeMarco Murray",
      "Derrick Henry",
      "Dion Lewis",
      "Dontrell Hilliard",
      "Eddie George",
      "Greg Comella",
      "Hassan Haskins",
      "Jackie Battle",
      "Jalston Fowler",
      "Jamie Harper",
      "Jarrett Payton",
      "Javon Ringer",
      "Jeremy McNichols",
      "John Simon",
      "Jonathan Ward",
      "Julius Chestnut",
      "Khari Blasingame",
      "LenDale White",
      "Leon Washington",
      "Lorenzo Neal",
      "Quinn Johnson",
      "Quinton Ganther",
      "Robert Holcombe",
      "Rodney Thomas",
      "Senorise Perry",
      "Shonn Greene",
      "Skip Hicks",
      "Terrance West",
      "Travis Henry",
      "Troy Fleming",
      "Tyjae Spears"
    ],
    "answer_count": 48
  },
  {
    "left_category": "pos_rb",
    "right_category": "team_cardinals",
    "left_label": "Running Back",
    "right_label": "Cardinals",
    "valid_players": [
      "A.J. Schable",
      "Adrian Murrell",
      "Adrian Peterson",
      "Alfonso Smith",
      "Alfred Morris",
      "Andre Ellington",
      "Anthony Sherman",
      "Bob Christian",
      "Brandon Wilds",
      "Bronson Hill",
      "Chase Edmonds",
      "Chester Taylor",
      "Chris Johnson",
      "Chris Wells",
      "Clarence Williams",
      "Corey Clement",
      "D.J. Foster",
      "Damien Anderson",
      "Damien Williams",
      "Dan Kreider",
      "Darrel Williams",
      "David Johnson",
      "Dennis McKinley",
      "Derrick Coleman",
      "Edgerrin James",
      "Elijhaa Penny",
      "Emari Demercado",
      "Emmitt Smith",
      "Eno Benjamin",
      "Fred Taylor",
      "J.J. Arrington",
      "Jalen Parmele",
      "James Conner",
      "James Hodgins",
      "James Jackson",
      "Jarrod Baxter",
      "Jason Wright",
      "Jerome Johnson",
      "Joel Makovicka",
      "Jonathan Dwyer",
      "Jonathan Ward",
      "Josh Scobey",
      "Keaontay Ingram",
      "Kenyan Drake",
      "Kerwynn Williams",
      "LaRod Stephens-Howling",
      "Larry Croom",
      "Marcel Shipp",
      "Mario Bates",
      "Marion Grice",
      "Michael Carter",
      "Michael Pittman",
      "Obafemi Ayanbadejo",
      "Rashard Mendenhall",
      "Reagan Maui'a",
      "Robert Hughes",
      "Ryan Williams",
      "Stepfan Taylor",
      "Steve Bush",
      "T.J. Logan",
      "Terrelle Smith",
      "Thomas Jones",
      "Tim Castille",
      "Tim Hightower",
      "Tony Jones",
      "Troy Hambrick",
      "Ty'Son Williams",
      "William Powell"
    ],
    "answer_count": 68
  },
  {
    "left_category": "team_cardinals",
    "right_category": "pick1",
    "left_label": "Cardinals",
    "right_label": "#1 Overall Pick",
    "valid_players": [
      "Carson Palmer",
      "Derrick Coleman"
    ],
    "answer_count": 2
  },
  {
    "left_category": "pick1",
    "right_category": "nhl_wings",
    "left_label": "#1 Overall Pick",
    "right_label": "Red Wings",
    "valid_players": [
      "Joe Murphy",
      "Mike Modano",
      "Patrick Kane"
    ],
    "answer_count": 3
  },
  {
    "left_category": "nhl_wings",
    "right_category": "top5",
    "left_label": "Red Wings",
    "right_label": "Top 5 Pick",
    "valid_players": [
      "Aaron Ward",
      "Bobby Ryan",
      "Brad Stuart",
      "Brendan Shanahan",
      "David Legwand",
      "James van Riemsdyk",
      "Joe Murphy",
      "Keith Primeau",
      "Larry Murphy",
      "Lucas Raymond",
      "Mike Modano",
      "Olli Juolevi",
      "Patrick Kane",
      "Stephen Weiss",
      "Steve Yzerman",
      "Thomas Vanek"
    ],
    "answer_count": 16
  }
]